keycloak_admin_aio/__init__.py
keycloak_admin_aio/__version__.py
keycloak_admin_aio/_httpx_args.py
keycloak_admin_aio/_keycloak_admin_aio.py
keycloak_admin_aio/py.typed
keycloak_admin_aio/_lib/utils.py
keycloak_admin_aio/_resources/__init__.py
keycloak_admin_aio/_resources/keycloak_resource.py
keycloak_admin_aio/_resources/admin_events/__init__.py
keycloak_admin_aio/_resources/admin_events/admin_events.py
keycloak_admin_aio/_resources/attack_detection/__init__.py
keycloak_admin_aio/_resources/attack_detection/attack_detection.py
keycloak_admin_aio/_resources/attack_detection/brute_force/__init__.py
keycloak_admin_aio/_resources/attack_detection/brute_force/brute_force.py
keycloak_admin_aio/_resources/attack_detection/brute_force/users/__init__.py
keycloak_admin_aio/_resources/attack_detection/brute_force/users/users.py
keycloak_admin_aio/_resources/attack_detection/brute_force/users/by_id/__init__.py
keycloak_admin_aio/_resources/attack_detection/brute_force/users/by_id/by_id.py
keycloak_admin_aio/_resources/authentication/__init__.py
keycloak_admin_aio/_resources/authentication/authentication.py
keycloak_admin_aio/_resources/authentication/required_actions/__init__.py
keycloak_admin_aio/_resources/authentication/required_actions/required_actions.py
keycloak_admin_aio/_resources/client_scopes/__init__.py
keycloak_admin_aio/_resources/client_scopes/client_scopes.py
keycloak_admin_aio/_resources/client_scopes/by_id/__init__.py
keycloak_admin_aio/_resources/client_scopes/by_id/by_id.py
keycloak_admin_aio/_resources/client_scopes/by_id/scope_mappings/__init__.py
keycloak_admin_aio/_resources/client_scopes/by_id/scope_mappings/scope_mappings.py
keycloak_admin_aio/_resources/client_scopes/by_id/scope_mappings/realm/__init__.py
keycloak_admin_aio/_resources/client_scopes/by_id/scope_mappings/realm/realm.py
keycloak_admin_aio/_resources/clients/__init__.py
keycloak_admin_aio/_resources/clients/clients.py
keycloak_admin_aio/_resources/clients/by_id/__init__.py
keycloak_admin_aio-1.3.7.dist-info/LICENSE
keycloak_admin_aio-1.3.7.dist-info/METADATA
keycloak_admin_aio-1.3.7.dist-info/WHEEL
keycloak_admin_aio-1.3.7.dist-info/top_level.txt
keycloak_admin_aio-1.3.7.dist-info/RECORD
