Metadata-Version: 2.1
Name: keycloak-admin-aio
Version: 1.3.7
Summary: async keycloak admin api wrapper
Author-email: Nicklas Sedlock <nicklas.sedlock@posteo.net>
License: Apache License
Project-URL: Documentation, https://v-mann-nick.github.io/keycloak-admin-aio/
Project-URL: Repository, https://github.com/V-Mann-Nick/keycloak-admin-aio.git
Project-URL: Issues, https://github.com/V-Mann-Nick/keycloak-admin-aio/issues
Project-URL: Changelog, https://github.com/V-Mann-Nick/keycloak-admin-aio/blob/main/CHANGELOG.md
Requires-Python: >=3.9
License-File: LICENSE
Requires-Dist: httpx >=0.23.3
Requires-Dist: dacite >=1.6.0
